zoloto/__init__.py
zoloto/__main__.py
zoloto/calibration.py
zoloto/coords.py
zoloto/exceptions.py
zoloto/marker.py
zoloto/marker_type.py
zoloto/py.typed
zoloto/utils.py
zoloto/cameras/__init__.py
zoloto/cameras/base.py
zoloto/cameras/camera.py
zoloto/cameras/file.py
zoloto/cameras/marker.py
zoloto/cameras/mixins.py
zoloto/cameras/rpi.py
zoloto/cameras/utils.py
zoloto/cli/__init__.py
zoloto/cli/annotate_image.py
zoloto/cli/annotate_video.py
zoloto/cli/count_markers.py
zoloto/cli/marker_details.py
zoloto/cli/marker_pdfs.py
zoloto/cli/preview.py
zoloto/cli/save_markers.py
zoloto/cli/validate_calibration.py
zoloto-0.9.0.dist-info/LICENSE
zoloto-0.9.0.dist-info/METADATA
zoloto-0.9.0.dist-info/WHEEL
zoloto-0.9.0.dist-info/entry_points.txt
zoloto-0.9.0.dist-info/top_level.txt
zoloto-0.9.0.dist-info/RECORD
