Metadata-Version: 2.1
Name: zoloto
Version: 0.9.0
Summary: A fiducial marker system powered by OpenCV - Supports ArUco and April
Home-page: https://github.com/RealOrangeOne/zoloto
Author: Jake Howard
License: BSD
Project-URL: Changelog, https://github.com/RealOrangeOne/zoloto/releases
Project-URL: Documentation, https://zoloto.readthedocs.io/
Project-URL: Source, https://github.com/RealOrangeOne/zoloto
Project-URL: Issues, https://github.com/RealOrangeOne/zoloto/issues
Classifier: Development Status :: 4 - Beta
Classifier: Intended Audience :: Developers
Classifier: Intended Audience :: Education
Classifier: Intended Audience :: Information Technology
Classifier: Intended Audience :: Science/Research
Classifier: Programming Language :: Python
Classifier: Programming Language :: Python :: 3
Classifier: Programming Language :: Python :: 3.8
Classifier: Programming Language :: Python :: 3.9
Classifier: Programming Language :: Python :: 3.10
Classifier: Programming Language :: Python :: Implementation :: CPython
Classifier: Topic :: Scientific/Engineering
Classifier: Topic :: Scientific/Engineering :: Image Recognition
Classifier: Topic :: Software Development
Classifier: Typing :: Typed
Requires-Python: >=3.8
License-File: LICENSE
Requires-Dist: cached-property (>=1.5)
Requires-Dist: pyquaternion (>=0.9.2)
Requires-Dist: numpy (>=1.22)
Provides-Extra: cli
Requires-Dist: Pillow ; extra == 'cli'
Requires-Dist: tqdm ; extra == 'cli'
Provides-Extra: opencv
Requires-Dist: opencv-contrib-python (<4.6,>=4.0) ; extra == 'opencv'
Provides-Extra: rpi
Requires-Dist: picamera[array] (>=1.13) ; extra == 'rpi'
